{
  "Parent": "Template_Weapon_Sword",
  "TranslationProperties": {
    "Name": "Star Wrath"
  },
  "Model": "Items/Weapons/StarWrath/StarWrath.blockymodel",
  "Texture": "Items/Weapons/StarWrath/SrarWrath.png",
  "Quality": "Legendary",
  "ItemLevel": 50,
  "Icon": "Icons/ItemsGenerated/StarWrath.png",
  "Recipe": {
    "TimeSeconds": 5,
    "KnowledgeRequired": false,
    "Input": [
      {
        "ItemId": "Ingredient_Crystal_Purple",
        "Quantity": 20
      },
      {
        "ItemId": "Ingredient_Bar_Gold",
        "Quantity": 10
      },
      {
        "ItemId": "Ingredient_FallenStar",
        "Quantity": 20
      },
      {
        "ItemId": "Ingredient_Bar_Adamantite",
        "Quantity": 30
      }
    ],
    "BenchRequirement": [
      {
        "Type": "Crafting",
        "Categories": [
          "Weapon_Sword"
        ],
        "Id": "Weapon_Bench",
        "RequiredTierLevel": 3
      }
    ],
    "RequiredMemoriesLevel": 6
  },
  "IconProperties": {
    "Scale": 0.35,
    "Rotation": [
      45,
      90,
      0
    ],
    "Translation": [
      -35,
      -35
    ]
  },
  "InteractionVars": {
    "Swing_Left": {
      "Interactions": [
        "Weapon_Sword_Primary_Swing_Left",
        {
          "Type": "StarWrath"
        }
      ]
    },
    "Swing_Right": {
      "Interactions": [
        "Weapon_Sword_Primary_Swing_Right",
        {
          "Type": "StarWrath"
        }
      ]
    },
    "Swing_Down": {
      "Interactions": [
        "Weapon_Sword_Primary_Swing_Down",
        {
          "Type": "StarWrath"
        }
      ]
    },
    "Swing_Left_Damage": {
      "Interactions": [
        {
          "Parent": "Weapon_Sword_Primary_Swing_Left_Damage",
          "DamageCalculator": {
            "BaseDamage": {
              "Physical": 18
            }
          },
          "DamageEffects": {
            "WorldSoundEventId": "SFX_Sword_T2_Impact",
            "LocalSoundEventId": "SFX_Sword_T2_Impact"
          }
        }
      ]
    },
    "Swing_Right_Damage": {
      "Interactions": [
        {
          "Parent": "Weapon_Sword_Primary_Swing_Right_Damage",
          "DamageCalculator": {
            "BaseDamage": {
              "Physical": 21
            }
          },
          "DamageEffects": {
            "WorldSoundEventId": "SFX_Sword_T2_Impact",
            "LocalSoundEventId": "SFX_Sword_T2_Impact"
          }
        }
      ]
    },
    "Swing_Down_Damage": {
      "Interactions": [
        {
          "Parent": "Weapon_Sword_Primary_Swing_Down_Damage",
          "DamageCalculator": {
            "BaseDamage": {
              "Physical": 34
            }
          },
          "DamageEffects": {
            "WorldSoundEventId": "SFX_Sword_T2_Impact",
            "LocalSoundEventId": "SFX_Sword_T2_Impact"
          }
        }
      ]
    },
    "Thrust_Damage": {
      "Interactions": [
        {
          "Parent": "Weapon_Sword_Primary_Thrust_Damage",
          "DamageCalculator": {
            "BaseDamage": {
              "Physical": 51
            }
          },
          "EntityStatsOnHit": [
            {
              "EntityStatId": "SignatureEnergy",
              "Amount": 3
            }
          ],
          "DamageEffects": {
            "WorldSoundEventId": "SFX_Sword_T2_Impact",
            "LocalSoundEventId": "SFX_Sword_T2_Impact"
          }
        }
      ]
    },
    "Vortexstrike_Spin_Damage": {
      "Interactions": [
        {
          "Parent": "Weapon_Sword_Signature_Vortexstrike_Spin_Damage",
          "DamageCalculator": {
            "BaseDamage": {
              "Physical": 37
            }
          },
          "EntityStatsOnHit": [],
          "DamageEffects": {
            "WorldSoundEventId": "SFX_Sword_T2_Impact",
            "LocalSoundEventId": "SFX_Sword_T2_Impact"
          }
        }
      ]
    },
    "Vortexstrike_Stab_Damage": {
      "Interactions": [
        {
          "Parent": "Weapon_Sword_Signature_Vortexstrike_Stab_Damage",
          "DamageCalculator": {
            "BaseDamage": {
              "Physical": 110
            }
          },
          "EntityStatsOnHit": [],
          "DamageEffects": {
            "WorldSoundEventId": "SFX_Sword_T2_Impact",
            "LocalSoundEventId": "SFX_Sword_T2_Impact"
          }
        }
      ]
    },
    "Guard_Wield": {
      "Interactions": [
        {
          "Parent": "Weapon_Sword_Secondary_Guard_Wield",
          "StaminaCost": {
            "Value": 20,
            "CostType": "Damage"
          }
        }
      ]
    }
  },
  "MaxDurability": 220,
  "DurabilityLossOnHit": 0.21,
  "Interactions": {
    "Primary": "StarWrath_Root"
  },
  "SoundEventId": "StarWrath_AttackSound",
  "Scale": 1.3,
  "Trails": [
    {
      "TrailId": "StarWrathSword_Trail1",
      "PositionOffset": {
        "Y": 0.5
      }
    }
  ],
  "Particles": [
    {
      "SystemId": "Firework_GS",
      "Color": "#ff99df",
      "Scale": 0.2,
      "PositionOffset": {
        "Y": 0,
        "Z": 0
      }
    }
  ],
  "Light": {
    "Color": "#858"
  }
}
